co2_emissions_ml/__init__.py
co2_emissions_ml/evaluation.py
co2_emissions_ml/models.py
co2_emissions_ml/pipeline.py
co2_emissions_ml/preprocessing.py
co2_emissions_ml-1.0.1.dist-info/licenses/LICENSE
co2_emissions_ml-1.0.1.dist-info/METADATA
co2_emissions_ml-1.0.1.dist-info/WHEEL
co2_emissions_ml-1.0.1.dist-info/entry_points.txt
co2_emissions_ml-1.0.1.dist-info/top_level.txt
co2_emissions_ml-1.0.1.dist-info/RECORD
