Metadata-Version: 2.4
Name: co2_emissions_ml
Version: 1.0.1
Summary: End-to-end ML pipeline for vehicle CO2 emissions prediction
Home-page: https://github.com/Shashvat-Jain/CO2-predictions-using-Automotive-Features/
Author: Shashvat Jain
Author-email: 20je0897@mc.iitism.ac.in
Classifier: Programming Language :: Python :: 3.10
Classifier: License :: OSI Approved :: MIT License
License-File: LICENSE
Requires-Dist: numpy>=1.23
Requires-Dist: pandas>=1.5
Requires-Dist: scipy>=1.7.0
Requires-Dist: scikit-learn>=1.2
Requires-Dist: matplotlib>=3.5
Requires-Dist: seaborn>=0.12
Requires-Dist: lightgbm>=3.3
Requires-Dist: xgboost>=1.7
Requires-Dist: catboost>=1.1
Requires-Dist: optuna>=3.0
Requires-Dist: shap>=0.40
Requires-Dist: jupyterlab>=3.6
Dynamic: author
Dynamic: author-email
Dynamic: classifier
Dynamic: description
Dynamic: description-content-type
Dynamic: home-page
Dynamic: license-file
Dynamic: requires-dist
Dynamic: summary
